monopati/__init__.py
monopati/helpers.py
monopati/render.py
monopati/__pycache__/__init__.cpython-313.pyc
monopati/__pycache__/__init__.cpython-36.pyc
monopati/__pycache__/__init__.cpython-37.pyc
monopati/__pycache__/__init__.cpython-38.pyc
monopati/__pycache__/helpers.cpython-37.pyc
monopati/__pycache__/render.cpython-36.pyc
monopati/__pycache__/render.cpython-37.pyc
monopati/skel/config.yml.dist
monopati/skel/favicon.ico
monopati/skel/pages/index.html
monopati/skel/posts/helo_world.md
monopati/skel/posts/files/gnulaptop.png
monopati/skel/posts/files/tor-people.jpg
monopati/skel/static/css/app.css
monopati/skel/static/fonts/ClearSans-Bold.eot
monopati/skel/static/fonts/ClearSans-Bold.svg
monopati/skel/static/fonts/ClearSans-Bold.ttf
monopati/skel/static/fonts/ClearSans-Bold.woff
monopati/skel/static/fonts/ClearSans-BoldItalic.eot
monopati/skel/static/fonts/ClearSans-BoldItalic.svg
monopati/skel/static/fonts/ClearSans-BoldItalic.ttf
monopati/skel/static/fonts/ClearSans-BoldItalic.woff
monopati/skel/static/fonts/ClearSans-Italic.eot
monopati/skel/static/fonts/ClearSans-Italic.svg
monopati/skel/static/fonts/ClearSans-Italic.ttf
monopati/skel/static/fonts/ClearSans-Italic.woff
monopati/skel/static/fonts/ClearSans-Regular.eot
monopati/skel/static/fonts/ClearSans-Regular.svg
monopati/skel/static/fonts/ClearSans-Regular.ttf
monopati/skel/static/fonts/ClearSans-Regular.woff
monopati/skel/static/img/avatar.png
monopati/skel/static/js/app.js
monopati/skel/static/lib/bootstrap/dist/css/bootstrap.min.css
monopati/skel/static/lib/bootstrap/dist/js/bootstrap.min.js
monopati/skel/static/lib/fork-awesome/css/fork-awesome.min.css
monopati/skel/static/lib/fork-awesome/fonts/forkawesome-webfont.eot
monopati/skel/static/lib/fork-awesome/fonts/forkawesome-webfont.svg
monopati/skel/static/lib/fork-awesome/fonts/forkawesome-webfont.ttf
monopati/skel/static/lib/fork-awesome/fonts/forkawesome-webfont.woff
monopati/skel/static/lib/fork-awesome/fonts/forkawesome-webfont.woff2
monopati-0.3.3.dist-info/licenses/LICENSE
monopati-0.3.3.dist-info/METADATA
monopati-0.3.3.dist-info/WHEEL
monopati-0.3.3.dist-info/top_level.txt
monopati-0.3.3.dist-info/RECORD
