Metadata-Version: 2.4
Name: monopati
Version: 0.3.3
Summary: a minimalistic static content generator
Home-page: https://codeberg.org/comzeradd/monopati
Author: Nikos Roussos
Author-email: nikos@roussos.cc
License: LICENSE
Classifier: Development Status :: 5 - Production/Stable
Classifier: Environment :: Console
Classifier: License :: OSI Approved :: GNU Affero General Public License v3
Classifier: Operating System :: OS Independent
Classifier: Programming Language :: Python :: 3 :: Only
Classifier: Topic :: Internet :: WWW/HTTP :: Site Management
License-File: LICENSE
Requires-Dist: docopt
Requires-Dist: Jinja2
Requires-Dist: Markdown
Requires-Dist: PyYAML
Dynamic: author
Dynamic: author-email
Dynamic: classifier
Dynamic: description
Dynamic: home-page
Dynamic: license
Dynamic: license-file
Dynamic: requires-dist
Dynamic: summary
